{
    "name": "input",
    "include_guard": "INPUT",
    "classes": [
        {
            "name": "BaseInput",
            "attributes": [
                {
                    "data_type": "ID",
                    "names": "id",
                    "description": "ID of the object"
                }
            ]
        },
        {
            "name": "NodeInput",
            "base": "BaseInput",
            "attributes": [
                {
                    "data_type": "double",
                    "names": "u_rated",
                    "description": "Rated line-line voltage"
                }
            ]
        },
        {
            "name": "BranchInput",
            "base": "BaseInput",
            "attributes": [
                {
                    "data_type": "ID",
                    "names": [
                        "from_node",
                        "to_node"
                    ],
                    "description": "Node IDs to which this branch is connected at both sides"
                },
                {
                    "data_type": "IntS",
                    "names": [
                        "from_status",
                        "to_status"
                    ],
                    "description": "If the branch is connected at each side"
                }
            ]
        },
        {
            "name": "Branch3Input",
            "base": "BaseInput",
            "attributes": [
                {
                    "data_type": "ID",
                    "names": [
                        "node_1",
                        "node_2",
                        "node_3"
                    ],
                    "description": "Node IDs to which this branch3 is connected at three sides"
                },
                {
                    "data_type": "IntS",
                    "names": [
                        "status_1",
                        "status_2",
                        "status_3"
                    ],
                    "description": "If the branch is connected at each side"
                }
            ]
        },
        {
            "name": "ApplianceInput",
            "base": "BaseInput",
            "attributes": [
                {
                    "data_type": "ID",
                    "names": "node",
                    "description": "Node ID to which this appliance is connected"
                },
                {
                    "data_type": "IntS",
                    "names": "status",
                    "description": "If the appliance is connected"
                }
            ]
        },
        {
            "name": "LineInput",
            "base": "BranchInput",
            "attributes": [
                {
                    "data_type": "double",
                    "names": [
                        "r1",
                        "x1",
                        "c1",
                        "tan1"
                    ],
                    "description": "positive sequence parameters"
                },
                {
                    "data_type": "double",
                    "names": [
                        "r0",
                        "x0",
                        "c0",
                        "tan0"
                    ],
                    "description": "negative sequence parameters"
                },
                {
                    "data_type": "double",
                    "names": "i_n",
                    "description": "rated current"
                }
            ]
        },
        {
            "name": "LinkInput",
            "base": "BranchInput",
            "attributes": []
        },
        {
            "name": "TransformerInput",
            "base": "BranchInput",
            "attributes": [
                {
                    "data_type": "double",
                    "names": [
                        "u1",
                        "u2"
                    ],
                    "description": "rated voltage at both side"
                },
                {
                    "data_type": "double",
                    "names": "sn",
                    "description": "rated power"
                },
                {
                    "data_type": "double",
                    "names": ["uk", "pk", "i0", "p0"],
                    "description": "short circuit and open testing parameters"
                },
                {
                    "data_type": "WindingType",
                    "names": ["winding_from", "winding_to"],
                    "description": "winding type at each side"
                },
                {
                    "data_type": "IntS",
                    "names": "clock",
                    "description": "clock number"
                },
                {
                    "data_type": "BranchSide",
                    "names": "tap_side",
                    "description": "side of tap changer"
                },
                {
                    "data_type": "IntS",
                    "names": ["tap_pos", "tap_min", "tap_max", "tap_nom"],
                    "description": "tap changer parameters"
                },
                {
                    "data_type": "double",
                    "names": "tap_size",
                    "description": "size of each tap"
                },
                {
                    "data_type": "double",
                    "names": ["uk_min", "uk_max", "pk_min", "pk_max"],
                    "description": "tap dependent short circuit parameters"
                },
                {
                    "data_type": "double",
                    "names": ["r_grounding_from", "x_grounding_from", "r_grounding_to", "x_grounding_to"],
                    "description": "grounding information"
                }
            ]
        },
        {
            "name": "ThreeWindingTransformerInput",
            "base": "Branch3Input",
            "attributes": [
                {
                    "data_type": "double",
                    "names": [
                        "u1",
                        "u2",
                        "u3"
                    ],
                    "description": "rated voltage at three sides"
                },
                {
                    "data_type": "double",
                    "names": ["sn_1", "sn_2", "sn_3"],
                    "description": "rated power at each side"
                },
                {
                    "data_type": "double",
                    "names": ["uk_12", "uk_13", "uk_23", "pk_12", "pk_13", "pk_23", "i0", "p0"],
                    "description": "short circuit and open testing parameters"
                },
                {
                    "data_type": "WindingType",
                    "names": ["winding_1", "winding_2", "winding_3"],
                    "description": "winding type at each side"
                },
                {
                    "data_type": "IntS",
                    "names": ["clock_12", "clock_13"],
                    "description": "clock numbers"
                },
                {
                    "data_type": "Branch3Side",
                    "names": "tap_side",
                    "description": "side of tap changer"
                },
                {
                    "data_type": "IntS",
                    "names": ["tap_pos", "tap_min", "tap_max", "tap_nom"],
                    "description": "tap changer parameters"
                },
                {
                    "data_type": "double",
                    "names": "tap_size",
                    "description": "size of each tap"
                },
                {
                    "data_type": "double",
                    "names": ["uk_12_min", "uk_12_max", "uk_13_min", "uk_13_max", "uk_23_min", "uk_23_max", "pk_12_min", "pk_12_max", "pk_13_min", "pk_13_max", "pk_23_min", "pk_23_max"],
                    "description": "tap dependent short circuit parameters"
                },
                {
                    "data_type": "double",
                    "names": ["r_grounding_1", "x_grounding_1", "r_grounding_2", "x_grounding_2", "r_grounding_3", "x_grounding_3"],
                    "description": "grounding information"
                }
            ]
        },
        {
            "name": "GenericLoadGenInput",
            "base": "ApplianceInput",
            "attributes": [
                {
                    "data_type": "LoadGenType",
                    "names": "type",
                    "description": "Type of the load_gen"
                }
            ]
        },
        {
            "name": "LoadGenInput",
            "base": "GenericLoadGenInput",
            "is_template": true,
            "attributes": [
                {
                    "data_type": "RealValue<sym>",
                    "names": [
                        "p_specified",
                        "q_specified"
                    ],
                    "description": "Specified active/reactive power"
                }
            ]
        }
    ]
}